spfluo_app/__init__.py
spfluo_app/__main__.py
spfluo_app-0.1.0.dist-info/METADATA
spfluo_app-0.1.0.dist-info/WHEEL
spfluo_app-0.1.0.dist-info/entry_points.txt
spfluo_app-0.1.0.dist-info/RECORD
